<?xml version="1.0" encoding="UTF-8"?>
<metadata xml:lang="en"><Esri><CreaDate>20220717</CreaDate><CreaTime>13202000</CreaTime><ArcGISFormat>1.0</ArcGISFormat><SyncOnce>FALSE</SyncOnce><DataProperties><itemProps><itemName Sync="TRUE">habitat_fl_stateplane.tif</itemName><itemLocation><linkage Sync="TRUE">file://C:\Users\chjch\Desktop\habitat\projected\habitat_fl_stateplane.tif</linkage><protocol Sync="TRUE">Local Area Network</protocol></itemLocation><imsContentType Sync="TRUE">002</imsContentType><nativeExtBox><westBL Sync="TRUE">2552142.066519</westBL><eastBL Sync="TRUE">2747220.416519</eastBL><southBL Sync="TRUE">158369.423496</southBL><northBL Sync="TRUE">350101.323496</northBL><exTypeCode Sync="TRUE">1</exTypeCode></nativeExtBox></itemProps><coordRef><type Sync="TRUE">Projected</type><geogcsn Sync="TRUE">GCS_North_American_1983</geogcsn><csUnits Sync="TRUE">Linear Unit: Foot_US (0.304801)</csUnits><projcsn Sync="TRUE">NAD_1983_StatePlane_Florida_North_FIPS_0903_Feet</projcsn><peXml Sync="TRUE">&lt;ProjectedCoordinateSystem xsi:type='typens:ProjectedCoordinateSystem' xmlns:xsi='http://www.w3.org/2001/XMLSchema-instance' xmlns:xs='http://www.w3.org/2001/XMLSchema' xmlns:typens='http://www.esri.com/schemas/ArcGIS/3.0.0'&gt;&lt;WKT&gt;PROJCS[&amp;quot;NAD_1983_StatePlane_Florida_North_FIPS_0903_Feet&amp;quot;,GEOGCS[&amp;quot;GCS_North_American_1983&amp;quot;,DATUM[&amp;quot;D_North_American_1983&amp;quot;,SPHEROID[&amp;quot;GRS_1980&amp;quot;,6378137.0,298.257222101]],PRIMEM[&amp;quot;Greenwich&amp;quot;,0.0],UNIT[&amp;quot;Degree&amp;quot;,0.0174532925199433]],PROJECTION[&amp;quot;Lambert_Conformal_Conic&amp;quot;],PARAMETER[&amp;quot;False_Easting&amp;quot;,1968500.0],PARAMETER[&amp;quot;False_Northing&amp;quot;,0.0],PARAMETER[&amp;quot;Central_Meridian&amp;quot;,-84.5],PARAMETER[&amp;quot;Standard_Parallel_1&amp;quot;,29.58333333333333],PARAMETER[&amp;quot;Standard_Parallel_2&amp;quot;,30.75],PARAMETER[&amp;quot;Latitude_Of_Origin&amp;quot;,29.0],UNIT[&amp;quot;Foot_US&amp;quot;,0.3048006096012192],AUTHORITY[&amp;quot;EPSG&amp;quot;,2238]]&lt;/WKT&gt;&lt;XOrigin&gt;-125939000&lt;/XOrigin&gt;&lt;YOrigin&gt;-91453300&lt;/YOrigin&gt;&lt;XYScale&gt;35209816.682919256&lt;/XYScale&gt;&lt;ZOrigin&gt;-100000&lt;/ZOrigin&gt;&lt;ZScale&gt;10000&lt;/ZScale&gt;&lt;MOrigin&gt;-100000&lt;/MOrigin&gt;&lt;MScale&gt;10000&lt;/MScale&gt;&lt;XYTolerance&gt;0.0032808333333333331&lt;/XYTolerance&gt;&lt;ZTolerance&gt;0.001&lt;/ZTolerance&gt;&lt;MTolerance&gt;0.001&lt;/MTolerance&gt;&lt;HighPrecision&gt;true&lt;/HighPrecision&gt;&lt;WKID&gt;102660&lt;/WKID&gt;&lt;LatestWKID&gt;2238&lt;/LatestWKID&gt;&lt;/ProjectedCoordinateSystem&gt;</peXml></coordRef><RasterProperties><General><PixelDepth Sync="TRUE">8</PixelDepth><HasColormap Sync="TRUE">FALSE</HasColormap><CompressionType Sync="TRUE">LZW</CompressionType><NumBands Sync="TRUE">1</NumBands><Format Sync="TRUE">TIFF</Format><HasPyramids Sync="TRUE">TRUE</HasPyramids><SourceType Sync="TRUE">discrete</SourceType><PixelType Sync="TRUE">unsigned integer</PixelType><NoDataValue Sync="TRUE">256</NoDataValue></General></RasterProperties><lineage><Process ToolSource="c:\program files\arcgis\pro\Resources\ArcToolbox\toolboxes\Data Management Tools.tbx\ProjectRaster" Date="20220717" Time="132020">ProjectRaster habitat.tif C:\Users\chjch\Desktop\habitat\projected\habitat_fl_stateplane.tif PROJCS["NAD_1983_StatePlane_Florida_North_FIPS_0903_Feet",GEOGCS["GCS_North_American_1983",DATUM["D_North_American_1983",SPHEROID["GRS_1980",6378137.0,298.257222101]],PRIMEM["Greenwich",0.0],UNIT["Degree",0.0174532925199433]],PROJECTION["Lambert_Conformal_Conic"],PARAMETER["False_Easting",1968500.0],PARAMETER["False_Northing",0.0],PARAMETER["Central_Meridian",-84.5],PARAMETER["Standard_Parallel_1",29.58333333333333],PARAMETER["Standard_Parallel_2",30.75],PARAMETER["Latitude_Of_Origin",29.0],UNIT["Foot_US",0.3048006096012192]] "Nearest neighbor" "98.425 98.425" NAD_1983_To_HARN_Florida # PROJCS["NAD_1983_HARN_Albers",GEOGCS["GCS_North_American_1983_HARN",DATUM["D_North_American_1983_HARN",SPHEROID["GRS_1980",6378137.0,298.257222101]],PRIMEM["Greenwich",0.0],UNIT["Degree",0.0174532925199433]],PROJECTION["Albers"],PARAMETER["False_Easting",400000.0],PARAMETER["False_Northing",0.0],PARAMETER["central_meridian",-84.0],PARAMETER["Standard_Parallel_1",24.0],PARAMETER["Standard_Parallel_2",31.5],PARAMETER["latitude_of_origin",24.0],UNIT["Meter",1.0]] NO_VERTICAL</Process></lineage></DataProperties><SyncDate>20220717</SyncDate><SyncTime>13202000</SyncTime><ModDate>20220717</ModDate><ModTime>13202000</ModTime></Esri><dataIdInfo><envirDesc Sync="TRUE">Microsoft Windows 10 Version 10.0 (Build 22000) ; Esri ArcGIS 13.0.0.36056</envirDesc><dataLang><languageCode value="eng" Sync="TRUE"></languageCode><countryCode value="USA" Sync="TRUE"></countryCode></dataLang><idCitation><resTitle Sync="TRUE">habitat_fl_stateplane.tif</resTitle><presForm><PresFormCd value="005" Sync="TRUE"></PresFormCd></presForm></idCitation><spatRpType><SpatRepTypCd value="002" Sync="TRUE"></SpatRepTypCd></spatRpType><dataExt><geoEle><GeoBndBox esriExtentType="search"><exTypeCode Sync="TRUE">1</exTypeCode><westBL Sync="TRUE">-82.666772</westBL><eastBL Sync="TRUE">-82.041208</eastBL><northBL Sync="TRUE">29.949715</northBL><southBL Sync="TRUE">29.412499</southBL></GeoBndBox></geoEle></dataExt></dataIdInfo><mdLang><languageCode value="eng" Sync="TRUE"></languageCode><countryCode value="USA" Sync="TRUE"></countryCode></mdLang><mdChar><CharSetCd value="004" Sync="TRUE"></CharSetCd></mdChar><distInfo><distFormat><formatName Sync="TRUE">Raster Dataset</formatName></distFormat></distInfo><mdHrLv><ScopeCd value="005" Sync="TRUE"></ScopeCd></mdHrLv><mdHrLvName Sync="TRUE">dataset</mdHrLvName><refSysInfo><RefSystem><refSysID><identCode code="2238" Sync="TRUE"></identCode><idCodeSpace Sync="TRUE">EPSG</idCodeSpace><idVersion Sync="TRUE">5.3(9.0.0)</idVersion></refSysID></RefSystem></refSysInfo><spatRepInfo><Georect><cellGeo><CellGeoCd Sync="TRUE" value="002"></CellGeoCd></cellGeo><numDims Sync="TRUE">2</numDims><tranParaAv Sync="TRUE">1</tranParaAv><chkPtAv Sync="TRUE">0</chkPtAv><cornerPts><pos Sync="TRUE">2552142.066519 158369.423496</pos></cornerPts><cornerPts><pos Sync="TRUE">2552142.066519 350101.323496</pos></cornerPts><cornerPts><pos Sync="TRUE">2747220.416519 350101.323496</pos></cornerPts><cornerPts><pos Sync="TRUE">2747220.416519 158369.423496</pos></cornerPts><centerPt><pos Sync="TRUE">2649681.241519 254235.373496</pos></centerPt><axisDimension type="002"><dimSize Sync="TRUE">1982</dimSize><dimResol><value Sync="TRUE" uom="ftUS">98.425000</value></dimResol></axisDimension><axisDimension type="001"><dimSize Sync="TRUE">1948</dimSize><dimResol><value Sync="TRUE" uom="ftUS">98.425000</value></dimResol></axisDimension><ptInPixel><PixOrientCd Sync="TRUE" value="001"></PixOrientCd></ptInPixel></Georect></spatRepInfo><eainfo><detailed Name="habitat_fl_stateplane.tif.vat"><enttyp><enttypl Sync="TRUE">habitat_fl_stateplane.tif.vat</enttypl><enttypt Sync="TRUE">Table</enttypt><enttypc Sync="TRUE">27</enttypc></enttyp><attr><attrlabl Sync="TRUE">OID</attrlabl><attalias Sync="TRUE">OID</attalias><attrtype Sync="TRUE">OID</attrtype><attwidth Sync="TRUE">4</attwidth><atprecis Sync="TRUE">0</atprecis><attscale Sync="TRUE">0</attscale><attrdef Sync="TRUE">Internal feature number.</attrdef><attrdefs Sync="TRUE">Esri</attrdefs><attrdomv><udom Sync="TRUE">Sequential unique whole numbers that are automatically generated.</udom></attrdomv></attr><attr><attrlabl Sync="TRUE">Value</attrlabl><attalias Sync="TRUE">Value</attalias><attrtype Sync="TRUE">Integer</attrtype><attwidth Sync="TRUE">10</attwidth><atprecis Sync="TRUE">10</atprecis><attscale Sync="TRUE">0</attscale></attr><attr><attrlabl Sync="TRUE">Count</attrlabl><attalias Sync="TRUE">Count</attalias><attrtype Sync="TRUE">Double</attrtype><attwidth Sync="TRUE">19</attwidth><atprecis Sync="TRUE">0</atprecis><attscale Sync="TRUE">0</attscale></attr></detailed></eainfo><contInfo><ImgDesc><contentTyp><ContentTypCd Sync="TRUE" value="002"></ContentTypCd></contentTyp><covDim><Band><dimDescrp Sync="TRUE">Band_1</dimDescrp><maxVal Sync="TRUE">255.000000</maxVal><minVal Sync="TRUE">0.000000</minVal><bitsPerVal Sync="TRUE">8</bitsPerVal><valUnit><UOM type="length"></UOM></valUnit></Band></covDim></ImgDesc></contInfo><mdDateSt Sync="TRUE">20220717</mdDateSt></metadata>
